{"type": "FeatureCollection", "features": [{"type": "Feature", "geometry": {"type": "Point", "coordinates": [-0.0865, 51.5106]}, "properties": {"type": "association", "num": 18, "layername": "Association", "mapid": "044-G-05204", "city": "London", "instinfo": "0010"}}, {"type": "Feature", "geometry": {"type": "Point", "coordinates": [2.3482, 48.8581]}, "properties": {"type": "association", "num": 17, "layername": "Association", "mapid": "033-G-18561", "city": "Paris", "instinfo": "1010"}}, {"type": "Feature", "geometry": {"type": "Point", "coordinates": [13.4154, 52.5223]}, "properties": {"type": "association", "num": 8, "layername": "Association", "mapid": "049-G-39307", "city": "Berlin", "instinfo": "0010"}}]}